tomographic_kernel/__init__.py
tomographic_kernel/fourier_kernel.py
tomographic_kernel/frames.py
tomographic_kernel/plotting.py
tomographic_kernel/tests.py
tomographic_kernel/tomographic_kernel.py
tomographic_kernel/utils.py
tomographic_kernel/models/__init__.py
tomographic_kernel/models/cannonical_models.py
tomographic_kernel/models/tests/__init__.py
tomographic_kernel/models/tests/test_directional_scale.py
tomographic_kernel/models/tests/test_time_scale.py
tomographic_kernel/simulation/__init__.py
tomographic_kernel/simulation/interpolate_h5parm.py
tomographic_kernel/simulation/ionosphere_simulation.py
tomographic_kernel/tests/__init__.py
tomographic_kernel/tests/test_frames.py
tomographic_kernel/tests/test_geometry.py
tomographic_kernel-1.0.4.dist-info/LICENSE
tomographic_kernel-1.0.4.dist-info/METADATA
tomographic_kernel-1.0.4.dist-info/WHEEL
tomographic_kernel-1.0.4.dist-info/top_level.txt
tomographic_kernel-1.0.4.dist-info/RECORD
