Metadata-Version: 2.1
Name: tomographic_kernel
Version: 1.0.4
Summary: A Tomographic Kernel in JAX for tomographic Gaussian processes.
Home-page: https://github.com/JoshuaAlbert/tomographic_kernel
Author: Joshua G. Albert
Author-email: albert@strw.leidenuniv.nl
Classifier: Programming Language :: Python :: 3
Classifier: License :: OSI Approved :: Apache Software License
Classifier: Operating System :: OS Independent
Requires-Python: >=3.8
License-File: LICENSE
Requires-Dist: numpy
Requires-Dist: h5parm >=1.0.5
Requires-Dist: scipy
Requires-Dist: astropy >=6
Requires-Dist: matplotlib
Requires-Dist: cmocean
Requires-Dist: tqdm
Requires-Dist: jax
Requires-Dist: jaxlib
Requires-Dist: tensorflow-probability
